context_compactor/__init__.py
context_compactor/adapters/__init__.py
context_compactor/adapters/claude_agent.py
context_compactor/adapters/openai_agents.py
context_compactor/adapters/pydantic_ai.py
context_compactor/core/__init__.py
context_compactor/core/compactor.py
context_compactor/core/hooks.py
context_compactor/core/protocols.py
context_compactor/core/types.py
context_compactor/strategies/__init__.py
context_compactor/strategies/generic.py
context_compactor/strategies/pydantic_ai.py
context_compactor/tokenizers/__init__.py
context_compactor/tokenizers/claude_agent.py
context_compactor/tokenizers/openai_agents.py
context_compactor/tokenizers/pydantic_ai.py
agentic_context_compaction-0.1.0.dist-info/METADATA
agentic_context_compaction-0.1.0.dist-info/WHEEL
agentic_context_compaction-0.1.0.dist-info/licenses/LICENSE
agentic_context_compaction-0.1.0.dist-info/RECORD
