Metadata-Version: 2.4
Name: agentic-context-compaction
Version: 0.1.0
Summary: Automatic context window management for AI agent SDKs
Project-URL: Homepage, https://github.com/cm2435/agentic_context_compaction
Project-URL: Repository, https://github.com/cm2435/agentic_context_compaction
Project-URL: Issues, https://github.com/cm2435/agentic_context_compaction/issues
Author-email: Charlie Masters <charlie.masters@deepflow.com>
License-Expression: MIT
License-File: LICENSE
Keywords: agents,ai,anthropic,claude,compaction,context,llm,openai,pydantic-ai
Classifier: Development Status :: 4 - Beta
Classifier: Intended Audience :: Developers
Classifier: License :: OSI Approved :: MIT License
Classifier: Programming Language :: Python :: 3
Classifier: Programming Language :: Python :: 3.11
Classifier: Programming Language :: Python :: 3.12
Classifier: Programming Language :: Python :: 3.13
Classifier: Topic :: Scientific/Engineering :: Artificial Intelligence
Classifier: Typing :: Typed
Requires-Python: >=3.11
Provides-Extra: all-sdks
Requires-Dist: claude-agent-sdk>=0.0.20; extra == 'all-sdks'
Requires-Dist: openai-agents>=0.0.3; extra == 'all-sdks'
Requires-Dist: pydantic-ai>=0.1.0; extra == 'all-sdks'
Provides-Extra: claude-agent
Requires-Dist: claude-agent-sdk>=0.0.20; extra == 'claude-agent'
Provides-Extra: dev
Requires-Dist: pytest-asyncio>=0.24.0; extra == 'dev'
Requires-Dist: pytest>=8.0.0; extra == 'dev'
Requires-Dist: ruff>=0.8.0; extra == 'dev'
Provides-Extra: full
Requires-Dist: context-compactor[all-sdks,dev,litellm,tiktoken]; extra == 'full'
Provides-Extra: litellm
Requires-Dist: litellm>=1.50.0; extra == 'litellm'
Provides-Extra: openai-agents
Requires-Dist: openai-agents>=0.0.3; extra == 'openai-agents'
Provides-Extra: pydantic-ai
Requires-Dist: pydantic-ai>=0.1.0; extra == 'pydantic-ai'
Provides-Extra: tiktoken
Requires-Dist: tiktoken>=0.7.0; extra == 'tiktoken'
